LICENSE
MANIFEST.in
README.md
requirements.json
setup.py
lazydock/__init__.py
lazydock/__version__.py
lazydock/config.py
lazydock/utils.py
lazydock.egg-info/PKG-INFO
lazydock.egg-info/SOURCES.txt
lazydock.egg-info/dependency_links.txt
lazydock.egg-info/entry_points.txt
lazydock.egg-info/requires.txt
lazydock.egg-info/top_level.txt
lazydock/algorithm/__init__.py
lazydock/algorithm/prs.py
lazydock/algorithm/rms.py
lazydock/algorithm/utils.py
lazydock/gmx/__init__.py
lazydock/gmx/run.py
lazydock/gmx/mda/__init__.py
lazydock/gmx/mda/align.py
lazydock/gmx/mda/convert.py
lazydock/gmx/mda/dihedrals.py
lazydock/gmx/mda/gnm.py
lazydock/gmx/mda/utils.py
lazydock/gmx/thirdparty/__init__.py
lazydock/gmx/thirdparty/cgenff_charmm2gmx.py
lazydock/gmx/thirdparty/sort_mol2_bonds.py
lazydock/pml/__init__.py
lazydock/pml/align_to_axis.py
lazydock/pml/autodock_utils.py
lazydock/pml/interaction_utils.py
lazydock/pml/ligplus_interaction.py
lazydock/pml/plip_interaction.py
lazydock/pml/rrcs.py
lazydock/pml/server.py
lazydock/pml/shader.py
lazydock/pml/utils.py
lazydock/pml/thirdparty/__init__.py
lazydock/pml/thirdparty/draw_bounding_box.py
lazydock/pml/thirdparty/modevectors.py
lazydock/pml_plugin/__init__.py
lazydock/pml_plugin/_init_.py
lazydock/pml_plugin/lazy_dlg.py
lazydock/pml_plugin/lazy_plot.py
lazydock/pml_plugin/lazy_pml.py
lazydock/pml_plugin/lazy_pocket.py
lazydock/pml_plugin/main.py
lazydock/pml_plugin/_nicegui/__init__.py
lazydock/pml_plugin/_nicegui/local_file_picker.py
lazydock/pyrt/__init__.py
lazydock/pyrt/energy_utils.py
lazydock/pyrt/pose_utils.py
lazydock/pyrt/relax.py
lazydock/pyrt/select_utils.py
lazydock/scripts/__init__.py
lazydock/scripts/__main__.py
lazydock/scripts/_main_.py
lazydock/scripts/_script_utils_.py
lazydock/scripts/align_pose_to_axis.py
lazydock/scripts/ana_gmx.py
lazydock/scripts/ana_interaction.py
lazydock/scripts/distribute_file.py
lazydock/scripts/dock.py
lazydock/scripts/eval_modeling.py
lazydock/scripts/get_pocket.py
lazydock/scripts/md_ana.py
lazydock/scripts/md_task.py
lazydock/scripts/md_traj.py
lazydock/scripts/prepare_gmx.py
lazydock/scripts/prepare_lig.py
lazydock/scripts/run_gmx.py
lazydock/scripts/sort_mol2_bonds.py
