Metadata-Version: 2.1
Name: lazydock
Version: 0.14.0
Summary: A Python package for molecular docking
Home-page: https://github.com/BHM-Bob/LazyDock
Author: BHM-Bob G
Author-email: bhmfly@foxmail.com
License: MIT Licence
Keywords: molecular docking,Utilities
Platform: any
Classifier: Development Status :: 4 - Beta
Classifier: Intended Audience :: Science/Research
Classifier: Topic :: Utilities
Classifier: License :: OSI Approved :: MIT License
Classifier: Programming Language :: Python :: 3
Classifier: Programming Language :: Python :: 3.8
Classifier: Programming Language :: Python :: 3.9
Classifier: Programming Language :: Python :: 3.10
Classifier: Programming Language :: Python :: 3.11
Classifier: Programming Language :: Python :: 3.12
Requires-Python: >=3.7, <3.13
License-File: LICENSE
Requires-Dist: mbapy>=0.11.2
Requires-Dist: pygame
Requires-Dist: nicegui
Requires-Dist: openbabel-wheel
Requires-Dist: networkx>=3
Requires-Dist: DuIvyTools>=0.6.0
Requires-Dist: toml
Requires-Dist: MDAnalysis>=2.9.0
Provides-Extra: all
Requires-Dist: mbapy>=0.11.2; extra == "all"
Requires-Dist: pygame; extra == "all"
Requires-Dist: nicegui; extra == "all"
Requires-Dist: openbabel-wheel; extra == "all"
Requires-Dist: networkx>=3; extra == "all"
Requires-Dist: DuIvyTools>=0.6.0; extra == "all"
Requires-Dist: toml; extra == "all"
Requires-Dist: MDAnalysis>=2.9.0; extra == "all"
Requires-Dist: compas; extra == "all"
Requires-Dist: md-davis; extra == "all"
Requires-Dist: plip>=2.4.0; extra == "all"
Requires-Dist: lazydock_md_task>=0.2.1; extra == "all"
